ciscript/__init__.py
ciscript/_typing.py
ciscript/_utils.py
ciscript/github.py
ciscript/py.typed
ciscript/yaml.py
ciscript-0.1.2.dist-info/WHEEL
ciscript-0.1.2.dist-info/METADATA
ciscript-0.1.2.dist-info/RECORD
