Metadata-Version: 2.1
Name: ciscript
Version: 0.1.2
Summary: 
Author: Adrian Garcia Badaracco
Author-email: dev@adriangb.com
Requires-Python: >=3.7,<4
Classifier: Programming Language :: Python :: 3
Classifier: Programming Language :: Python :: 3.7
Classifier: Programming Language :: Python :: 3.8
Classifier: Programming Language :: Python :: 3.9
Classifier: Programming Language :: Python :: 3.10
Classifier: Programming Language :: Python :: 3.11
Requires-Dist: PyYAML (>=6.0)
Requires-Dist: pydantic (>=1.10.2)
Requires-Dist: typing-extensions (>=4.4.0); python_version < "3.10"
